pyrelate/__init__.py
pyrelate/hi.py
pyrelate-0.0.0.dist-info/METADATA
pyrelate-0.0.0.dist-info/WHEEL
pyrelate-0.0.0.dist-info/top_level.txt
pyrelate-0.0.0.dist-info/RECORD
