Metadata-Version: 2.1
Name: pyrelate
Version: 0.0.0
Summary: Scientific code to represent and learn on a collection of atomic environments
Home-page: UNKNOWN
Author: Jay Spendlove
Author-email: jayclark24@gmail.com
License: Academic Public License
Platform: UNKNOWN
Classifier: Development Status :: 1 - Planning
Classifier: Intended Audience :: Science/Research
Classifier: Natural Language :: English
Classifier: Programming Language :: Python
Classifier: Programming Language :: Python :: 3
Classifier: Programming Language :: Python :: 3.7
